terminaloptions/__init__.py
terminaloptions-1.0.1.dist-info/METADATA
terminaloptions-1.0.1.dist-info/WHEEL
terminaloptions-1.0.1.dist-info/licenses/LICENSE
terminaloptions-1.0.1.dist-info/RECORD
