Metadata-Version: 2.3
Name: terminaloptions
Version: 1.0.1
Summary: Menu for command line
Project-URL: Homepage, https://github.com/ciuliene/terminaloptions
Project-URL: Issues, https://github.com/ciuliene/terminaloptions/issues
Author-email: Giuliano Errico <errgioul2@gmail.com>
License-File: LICENSE
Classifier: License :: OSI Approved :: MIT License
Classifier: Operating System :: OS Independent
Classifier: Programming Language :: Python :: 3
Requires-Python: >=3.11
Requires-Dist: readchar==4.1.0
